test/__init__.py
test/local_test.py
test/test_wencai.py
wencai/__init__.py
wencai/core/__init__.py
wencai/core/cons.py
wencai/core/content.py
wencai/core/cookies.py
wencai/core/crawler.py
wencai/core/event.py
wencai/core/session.py
wencai/js/__init__.py
wencai/js/hexin.js
wencai-0.2.6.dist-info/LICENSE.md
wencai-0.2.6.dist-info/METADATA
wencai-0.2.6.dist-info/WHEEL
wencai-0.2.6.dist-info/top_level.txt
wencai-0.2.6.dist-info/RECORD
